expense_tracker/__init__.py
expense_tracker/api.py
expense_tracker/cli.py
expense_tracker/config.py
expense_tracker/db.py
expense_tracker_alzahedi-0.1.0.dist-info/entry_points.txt
expense_tracker_alzahedi-0.1.0.dist-info/METADATA
expense_tracker_alzahedi-0.1.0.dist-info/WHEEL
expense_tracker_alzahedi-0.1.0.dist-info/RECORD
