Metadata-Version: 2.1
Name: expense-tracker-alzahedi
Version: 0.1.0
Summary: 
Author: Alfurquan Zahedi
Author-email: alzahedi@microsoft.com
Requires-Python: >=3.10,<4.0
Classifier: Programming Language :: Python :: 3
Classifier: Programming Language :: Python :: 3.10
Classifier: Programming Language :: Python :: 3.11
Requires-Dist: rich (==10.7.0)
Requires-Dist: tinydb (==4.5.1)
Requires-Dist: typer (==0.3.2)
